<?xml version="1.0" encoding="UTF-8"?>
<metadata xml:lang="en"><Esri><CreaDate>20130403</CreaDate><CreaTime>16002400</CreaTime><ArcGISFormat>1.0</ArcGISFormat><SyncOnce>TRUE</SyncOnce><ModDate>20130403</ModDate><ModTime>184936</ModTime></Esri><dataIdInfo><idCitation><resTitle>Validate Address Point Upload</resTitle></idCitation></dataIdInfo><distInfo><distributor><distorFormat><formatName>ArcToolbox Tool</formatName></distorFormat></distributor></distInfo><tool name="Tool" displayname="Validate Address Point Upload" toolboxalias=""><parameters><param name="zip" displayname="Address point zip file" type="Required" direction="Input" datatype="File" expression="zip"><dialogReference>&lt;DIV STYLE="text-align:Left;"&gt;&lt;DIV&gt;&lt;P&gt;&lt;SPAN&gt;Unzips an uploaded file and runs validation checks. Appends the data to the correct county address point layer.&lt;/SPAN&gt;&lt;/P&gt;&lt;/DIV&gt;&lt;/DIV&gt;</dialogReference></param></parameters></tool></metadata>
